cdsspy/__init__.py
cdsspy/admin_calls.py
cdsspy/analysis_services.py
cdsspy/climate.py
cdsspy/gw.py
cdsspy/reference_tbl.py
cdsspy/structures.py
cdsspy/sw.py
cdsspy/telemetry.py
cdsspy/utils.py
cdsspy/water_rights.py
cdsspy-1.2.691.dist-info/LICENSE
cdsspy-1.2.691.dist-info/METADATA
cdsspy-1.2.691.dist-info/WHEEL
cdsspy-1.2.691.dist-info/top_level.txt
cdsspy-1.2.691.dist-info/RECORD
