Metadata-Version: 2.1
Name: cdsspy
Version: 1.2.691
Summary: Provides Python functions for discovering and requesting data from the CDSS REST API.
Author: Angus Watters
Classifier: Programming Language :: Python :: 3
Classifier: License :: OSI Approved :: MIT License
Classifier: Operating System :: OS Independent
Requires-Python: >=3.6
License-File: LICENSE
Requires-Dist: pandas
Requires-Dist: datetime
Requires-Dist: requests
Requires-Dist: geopandas
Requires-Dist: shapely
Requires-Dist: pyproj
